soapnormalizer/__init__.py
soapnormalizer/nomad_plugin.yaml
soapnormalizer/normalizer.py
nomad_normalizer_plugin_soap-1.0.1.dist-info/LICENSE
nomad_normalizer_plugin_soap-1.0.1.dist-info/METADATA
nomad_normalizer_plugin_soap-1.0.1.dist-info/WHEEL
nomad_normalizer_plugin_soap-1.0.1.dist-info/entry_points.txt
nomad_normalizer_plugin_soap-1.0.1.dist-info/top_level.txt
nomad_normalizer_plugin_soap-1.0.1.dist-info/RECORD
